{
  "titulo": "Lista de premiações vencidas paraThe Simpsons",
  "dados": {
    "The Simpsons": "The SimpsonsPrêmioVenceuAmerican Comedy Awards1Annie Awards32Australian Kids' Choice Awards5British Comedy Awards3Primetime Emmy Award34Environmental Media Awards9Genesis Awards6GLAAD Media Awards1Golden Reel Awards1Calçada da Fama de HollywoodAgraciadoInternational Monitor Awards9[1]Kids' Choice Awards2Peabody Awards2People's Choice Awards8Prism Awards1Satellite Awards1Saturn Awards1TCA Awards2Teen Choice Awards5UK Kids' Choice Awards1WGA Awards13Young Artist Awards1",
    "The Simpsons Movie": "The Simpsons MovieBritish Comedy Awards1Golden Trailer Awards1UK Kids' Choice Awards1National Movie Award1"
  },
  "origem_html": "Lista_de_prêmios_e_indicações_para_The_Simpsons_–_Wikipédia,_a_enciclopédia_livre.html"
}